MANIFEST.in
setup.py
django_vhost/__init__.py
django_vhost/settings.py
django_vhost/utils.py
django_vhost.egg-info/PKG-INFO
django_vhost.egg-info/SOURCES.txt
django_vhost.egg-info/dependency_links.txt
django_vhost.egg-info/not-zip-safe
django_vhost.egg-info/requires.txt
django_vhost.egg-info/top_level.txt
django_vhost/management/__init__.py
django_vhost/management/commands/__init__.py
django_vhost/management/commands/gen_apache.py
django_vhost/management/commands/gen_nginx.py
django_vhost/templates/django_vhost/apache-wsgi.conf
django_vhost/templates/django_vhost/nginx-fastcgi.conf