Metadata-Version: 1.0
Name: django-vhost
Version: 0.17
Summary: Generates virtual host configuration files for apache and nginx
Home-page: https://bitbucket.org/djangostars/django-vhost
Author: Vasyl Dizhak
Author-email: vasyl.dizhak@djangostars.com
License: BSD
Keywords: django nginx apache fastcgi wsgi
Platform: any
Classifier: Environment :: Web Environment
Classifier: Framework :: Django
Classifier: Intended Audience :: Developers
Classifier: License :: OSI Approved :: BSD License
Classifier: Operating System :: OS Independent
Classifier: Programming Language :: Python
Classifier: Topic :: Internet :: WWW/HTTP :: Dynamic Content
Classifier: Topic :: Software Development :: Libraries :: Python Modules
